LICENSE
README.md
setup.py
SturmLiouville.egg-info/PKG-INFO
SturmLiouville.egg-info/SOURCES.txt
SturmLiouville.egg-info/dependency_links.txt
SturmLiouville.egg-info/requires.txt
SturmLiouville.egg-info/top_level.txt
sturmliouville/__init__.py